dapla/__init__.py
dapla/magics/__init__.py
dapla/magics/blueprint.py
ssb_ipython_magics-0.0.3.dist-info/LICENSE
ssb_ipython_magics-0.0.3.dist-info/METADATA
ssb_ipython_magics-0.0.3.dist-info/WHEEL
ssb_ipython_magics-0.0.3.dist-info/top_level.txt
ssb_ipython_magics-0.0.3.dist-info/RECORD
